petlja_api/__init__.py
petlja_api/auth.py
petlja_api/competition.py
petlja_api/problem.py
petlja_api/submit.py
petlja_api/urls.py
petlja_api-0.4.0.dist-info/METADATA
petlja_api-0.4.0.dist-info/WHEEL
petlja_api-0.4.0.dist-info/licenses/LICENSE
petlja_api-0.4.0.dist-info/RECORD
