Metadata-Version: 2.4
Name: petlja_api
Version: 0.4.0
Summary: A python library for interacting with the petlja.org API
Project-URL: Homepage, https://github.com/PavleSekesan/petlja_api
Author-email: Pavle Sekešan <pavlesekesan@gmail.com>
License-File: LICENSE
Requires-Python: >=3.8
Requires-Dist: beautifulsoup4~=4.0
Requires-Dist: requests~=2.0
Provides-Extra: dev
Requires-Dist: pytest; extra == 'dev'
Requires-Dist: pytest-timeout; extra == 'dev'
Requires-Dist: python-dotenv; extra == 'dev'
